res_manager/__init__.py
res_manager/manager.py
res_manager-3.1.1.dist-info/METADATA
res_manager-3.1.1.dist-info/RECORD
res_manager-3.1.1.dist-info/WHEEL
res_manager-3.1.1.dist-info/top_level.txt
tests/__init__.py
tests/test_allfunctions.py
