Metadata-Version: 2.1
Name: res-manager
Version: 3.1.1
Summary: res-manager helps you to manage your experimental results data in a more convenient way.
Home-page: https://github.com/hosea1008/res_manager
Author: Hongshan Li
Author-email: lhs17@mails.tsinghua.edu.cn
Maintainer: 
Maintainer-email: 
License: GPLv3
Platform: all
Classifier: Development Status :: 5 - Production/Stable
Classifier: Operating System :: OS Independent
Classifier: Intended Audience :: Developers
Classifier: License :: OSI Approved :: GNU General Public License v3 (GPLv3)
Classifier: Programming Language :: Python
Classifier: Programming Language :: Python :: Implementation
Classifier: Programming Language :: Python :: 2
Classifier: Programming Language :: Python :: 2.7
Classifier: Programming Language :: Python :: 3
Classifier: Programming Language :: Python :: 3.4
Classifier: Programming Language :: Python :: 3.5
Classifier: Programming Language :: Python :: 3.6
Classifier: Topic :: Utilities
Classifier: Topic :: Software Development :: Libraries :: Python Modules
Requires-Dist: prettytable (>=0.7.2)
